src/config.py
src/db.py
src/main.py
src/notify.py
src/scraper.py
anitube_simple_notification-1.2.4.dist-info/COPYING
anitube_simple_notification-1.2.4.dist-info/METADATA
anitube_simple_notification-1.2.4.dist-info/WHEEL
anitube_simple_notification-1.2.4.dist-info/entry_points.txt
anitube_simple_notification-1.2.4.dist-info/top_level.txt
anitube_simple_notification-1.2.4.dist-info/RECORD
