Metadata-Version: 2.1
Name: anitube-simple-notification
Version: 1.2.4
Summary: Getting notification from anitube.in.ua.
Author-email: Kostiantyn Klochko <kklochko@protonmail.com>
License: GNU GENERAL PUBLIC LICENSE
Project-URL: Homepage, https://gitlab.com/KKlochko/anitube-simple-notification
Project-URL: Bug Tracker, https://gitlab.com/KKlochko/anitube-simple-notification/issues
Classifier: Programming Language :: Python :: 3
Classifier: License :: OSI Approved :: GNU General Public License v3 or later (GPLv3+)
Classifier: Operating System :: OS Independent
Requires-Python: >=3.10
License-File: COPYING
Requires-Dist: requests (~=2.28.2)
Requires-Dist: beautifulsoup4 (~=4.11.1)
Requires-Dist: notify-py (~=0.3.39)
Requires-Dist: rich (~=13.1.0)
Requires-Dist: tomli (~=2.0.1)
Requires-Dist: loguru (~=0.5.3)
Requires-Dist: platformdirs (~=3.0.0)
